setup.py
littelbitx0/__init__.py
littelbitx0.egg-info/PKG-INFO
littelbitx0.egg-info/SOURCES.txt
littelbitx0.egg-info/dependency_links.txt
littelbitx0.egg-info/top_level.txt