Metadata-Version: 2.1
Name: littelbitx0
Version: 1.1.0
Summary: package for pentesting
Author: non
